pyevonic/__init__.py
pyevonic/evonic.py
pyevonic/exceptions.py
pyevonic/models.py
pyevonic-0.0.21.dist-info/METADATA
pyevonic-0.0.21.dist-info/WHEEL
pyevonic-0.0.21.dist-info/top_level.txt
pyevonic-0.0.21.dist-info/RECORD
