Metadata-Version: 2.1
Name: pyevonic
Version: 0.0.21
Summary: A wrapper for the Evoflame API v1
Home-page: https://github.com/greghesp/python-evonic
Author: Greg Hesp
Author-email: greg.hesp+pyevonic@gmail.com
Classifier: Programming Language :: Python :: 3
Classifier: License :: OSI Approved :: Apache Software License
Classifier: Operating System :: OS Independent
Requires-Python: >=3.6
